isdd/__init__.py
isdd/callcode.py
isdd/isddfile.py
isdd/search.py
ISDD-0.0.0.1.dist-info/LICENSE
ISDD-0.0.0.1.dist-info/METADATA
ISDD-0.0.0.1.dist-info/WHEEL
ISDD-0.0.0.1.dist-info/top_level.txt
ISDD-0.0.0.1.dist-info/RECORD
