Metadata-Version: 2.1
Name: ISDD
Version: 0.0.0.1
Summary: ISDD package
Home-page: https://github.com/IsddCompany/ISDD
Author: Jjoon0513
Author-email: isddcompany@gmail.com
Keywords: ISDO,ISDD
Classifier: License :: OSI Approved :: MIT License
License-File: LICENSE
Requires-Dist: cython
